x402tools/__init__.py
x402tools/client.py
x402tools/exceptions.py
x402tools/types.py
x402tools-1.0.0.dist-info/METADATA
x402tools-1.0.0.dist-info/WHEEL
x402tools-1.0.0.dist-info/top_level.txt
x402tools-1.0.0.dist-info/RECORD
