Metadata-Version: 2.4
Name: x402tools
Version: 1.0.0
Summary: Python SDK for x402 Usage-Based Billing API
Home-page: https://github.com/JaspSoe/stakefy-usage-envelope
Author: Stakefy
Author-email: Stakefy <support@stakefy.com>
License: MIT
Project-URL: Homepage, https://github.com/JaspSoe/stakefy-usage-envelope
Project-URL: Documentation, https://github.com/JaspSoe/stakefy-usage-envelope
Project-URL: Repository, https://github.com/JaspSoe/stakefy-usage-envelope
Keywords: billing,api,usage,tracking,envelope,metering
Classifier: Development Status :: 4 - Beta
Classifier: Intended Audience :: Developers
Classifier: Topic :: Software Development :: Libraries :: Python Modules
Classifier: License :: OSI Approved :: MIT License
Classifier: Programming Language :: Python :: 3
Requires-Python: >=3.8
Requires-Dist: requests>=2.31.0
Dynamic: author
Dynamic: home-page
Dynamic: requires-python
